beautiful_report/__init__.py
beautiful_report/_version.py
beautiful_report/cli.py
beautiful_report/core.py
beautiful_report/decorators.py
beautiful_report/hooks.py
beautiful_report/plugin.py
beautiful_report/py.typed
beautiful_report/unittest_runner.py
beautiful_report/templates/report.html.jinja2
pytest_glow_report-0.1.0.dist-info/METADATA
pytest_glow_report-0.1.0.dist-info/WHEEL
pytest_glow_report-0.1.0.dist-info/entry_points.txt
pytest_glow_report-0.1.0.dist-info/licenses/LICENSE
pytest_glow_report-0.1.0.dist-info/RECORD
