Metadata-Version: 2.4
Name: pytest-glow-report
Version: 0.1.0
Summary: Beautiful, glowing HTML test reports for PyTest and unittest.
Project-URL: Homepage, https://github.com/godhiraj-code/pytest-glow-report
Project-URL: Repository, https://github.com/godhiraj-code/pytest-glow-report.git
Project-URL: Issues, https://github.com/godhiraj-code/pytest-glow-report/issues
Author-email: Dhiraj Das <dhirajdas.666@gmail.com>
License-Expression: MIT
License-File: LICENSE
Keywords: automation,html,pytest,report,testing,unittest
Classifier: Development Status :: 4 - Beta
Classifier: Framework :: Pytest
Classifier: Intended Audience :: Developers
Classifier: License :: OSI Approved :: MIT License
Classifier: Programming Language :: Python :: 3
Classifier: Programming Language :: Python :: 3.8
Classifier: Programming Language :: Python :: 3.9
Classifier: Programming Language :: Python :: 3.10
Classifier: Programming Language :: Python :: 3.11
Classifier: Programming Language :: Python :: 3.12
Classifier: Topic :: Software Development :: Quality Assurance
Classifier: Topic :: Software Development :: Testing
Requires-Python: >=3.8
Requires-Dist: jinja2>=3.0
Requires-Dist: typing-extensions>=4.0
Provides-Extra: dev
Requires-Dist: black; extra == 'dev'
Requires-Dist: mypy; extra == 'dev'
Requires-Dist: playwright; extra == 'dev'
Requires-Dist: pytest-regressions; extra == 'dev'
Requires-Dist: pytest>=6.0; extra == 'dev'
Requires-Dist: ruff; extra == 'dev'
Requires-Dist: sphinx; extra == 'dev'
Requires-Dist: tox; extra == 'dev'
Provides-Extra: pdf
Requires-Dist: weasyprint; extra == 'pdf'
Provides-Extra: pytest
Requires-Dist: pytest>=6.0; extra == 'pytest'
Provides-Extra: slack
Requires-Dist: slack-sdk; extra == 'slack'
